romann/__init__.py
romann/hiragana_english.json
romann/katakana_english.json
romann/romann.py
romann-0.1.3.dist-info/licenses/LICENSE
romann-0.1.3.dist-info/METADATA
romann-0.1.3.dist-info/WHEEL
romann-0.1.3.dist-info/top_level.txt
romann-0.1.3.dist-info/RECORD
