Metadata-Version: 2.4
Name: romann
Version: 0.1.3
Summary: 日本語→自然なローマ字・英語変換ライブラリ（kakasi/SudachiPyベース＋外来語辞書対応）
Author: ykuwa
License-Expression: MIT
Requires-Python: >=3.12
License-File: LICENSE
Requires-Dist: pykakasi
Requires-Dist: jaconv
Requires-Dist: sudachipy
Requires-Dist: sudachidict_core
Provides-Extra: dev
Requires-Dist: pytest; extra == "dev"
Requires-Dist: pytest-cov; extra == "dev"
Requires-Dist: flake8; extra == "dev"
Requires-Dist: pylint; extra == "dev"
Requires-Dist: black; extra == "dev"
Dynamic: license-file
